vectorlite/__init__.py
vectorlite/core.py
vectorlite/server.py
vectorlite-0.4.0.dist-info/LICENSE
vectorlite-0.4.0.dist-info/METADATA
vectorlite-0.4.0.dist-info/WHEEL
vectorlite-0.4.0.dist-info/entry_points.txt
vectorlite-0.4.0.dist-info/top_level.txt
vectorlite-0.4.0.dist-info/RECORD
