Metadata-Version: 2.1
Name: vectorlite
Version: 0.4.0
Summary: Lightweight vector database.
Home-page: http://vectorlitedb.com
Author: Collin Paran
License: Apache-2.0
Classifier: Programming Language :: Python :: 3
Classifier: License :: OSI Approved :: Apache Software License
Classifier: Operating System :: OS Independent
Requires-Python: >=3.6
License-File: LICENSE
Requires-Dist: numpy
Requires-Dist: sentence-transformers
Requires-Dist: torch
Requires-Dist: hnswlib
Requires-Dist: fastapi
Requires-Dist: uvicorn
Requires-Dist: joblib
Requires-Dist: python-multipart
Requires-Dist: langchain
Requires-Dist: pydantic
Requires-Dist: unstructured[all-docs]
